MANIFEST.in
README.rst
setup.py
figa/__init__.py
figa/typechecking.py
figa/util.py
figa.egg-info/PKG-INFO
figa.egg-info/SOURCES.txt
figa.egg-info/dependency_links.txt
figa.egg-info/requires.txt
figa.egg-info/top_level.txt
figa/loaders/__init__.py
figa/loaders/env.py
figa/loaders/hocon.py
figa/loaders/http.py
figa/loaders/ini.py
figa/loaders/json.py
figa/loaders/parser.py
figa/loaders/toml.py
figa/loaders/yaml.py