Metadata-Version: 1.2
Name: figa
Version: 0.1a5
Summary: Manage project configuration on multiple environments with ease.
Home-page: https://github.com/jpatrickdill/figa
Author: Patrick Dill <jamespatrickdill@gmail.com>
License: UNKNOWN
Keywords: config,ini,cfg,configure
Platform: UNKNOWN
Classifier: Development Status :: 3 - Alpha
Classifier: Intended Audience :: Developers
Classifier: License :: OSI Approved :: MIT License
Classifier: Programming Language :: Python :: 3
Classifier: Programming Language :: Python :: 3.4
Classifier: Programming Language :: Python :: 3.5
Classifier: Programming Language :: Python :: 3.6
Classifier: Programming Language :: Python :: 3.7
Classifier: Programming Language :: Python :: 3.8
Classifier: Programming Language :: Python :: 3 :: Only
Requires-Python: >=3.0, <4
